DWPoses/__init__.py
DWPoses/onnxdet.py
DWPoses/onnxpose.py
DWPoses/util.py
DWPoses/wholebody.py
dwposes-0.1.0.dist-info/licenses/LICENSE
dwposes-0.1.0.dist-info/METADATA
dwposes-0.1.0.dist-info/WHEEL
dwposes-0.1.0.dist-info/top_level.txt
dwposes-0.1.0.dist-info/RECORD
