Metadata-Version: 2.4
Name: DWPoses
Version: 0.1.0
Summary: Lightweight whole-body pose estimator (coords only) refactored from IDEA-Research/DWPose
Author-email: yefllower <yefllowers@gmail.com>
License: Apache-2.0
Project-URL: Homepage, https://github.com/yefllower/dwpose
Project-URL: Issues, https://github.com/yefllower/dwpose/issues
Requires-Python: >=3.9
License-File: LICENSE
Requires-Dist: torch>=2.0
Requires-Dist: opencv-python
Requires-Dist: Pillow
Requires-Dist: numpy
Dynamic: license-file
